ppopt/__init__.py
ppopt/critical_region.py
ppopt/mplp_program.py
ppopt/mpmilp_program.py
ppopt/mpmiqp_program.py
ppopt/mpmodel.py
ppopt/mpqp_program.py
ppopt/plot.py
ppopt/problem_generator.py
ppopt/solution.py
ppopt/solver.py
ppopt/geometry/__init__.py
ppopt/geometry/polytope.py
ppopt/geometry/polytope_operations.py
ppopt/mp_solvers/__init__.py
ppopt/mp_solvers/mitree.py
ppopt/mp_solvers/mpmiqp_enumeration.py
ppopt/mp_solvers/mpqp_ahmadi.py
ppopt/mp_solvers/mpqp_combi_graph.py
ppopt/mp_solvers/mpqp_combinatorial.py
ppopt/mp_solvers/mpqp_dist_combinatorial.py
ppopt/mp_solvers/mpqp_geometric.py
ppopt/mp_solvers/mpqp_graph.py
ppopt/mp_solvers/mpqp_parallel_combinatorial_exp.py
ppopt/mp_solvers/mpqp_parallel_geometric.py
ppopt/mp_solvers/mpqp_parallel_geometric_exp.py
ppopt/mp_solvers/mpqp_parrallel_combinatorial.py
ppopt/mp_solvers/mpqp_parrallel_graph.py
ppopt/mp_solvers/solve_mplp.py
ppopt/mp_solvers/solve_mpmiqp.py
ppopt/mp_solvers/solve_mpqp.py
ppopt/mp_solvers/solver_utils.py
ppopt/solver_interface/__init__.py
ppopt/solver_interface/cvxopt_interface.py
ppopt/solver_interface/daqp_solver_interface.py
ppopt/solver_interface/gurobi_solver_interface.py
ppopt/solver_interface/quad_prog_interface.py
ppopt/solver_interface/solver_interface.py
ppopt/solver_interface/solver_interface_utils.py
ppopt/upop/__init__.py
ppopt/upop/language_generation.py
ppopt/upop/linear_code_gen.py
ppopt/upop/point_location.py
ppopt/upop/ucontroller.py
ppopt/upop/upop_utils.py
ppopt/utils/__init__.py
ppopt/utils/chebyshev_ball.py
ppopt/utils/constraint_utilities.py
ppopt/utils/general_utils.py
ppopt/utils/geometric.py
ppopt/utils/mpqp_utils.py
ppopt/utils/region_overlap_utils.py
ppopt-1.6.12.dist-info/LICENSE
ppopt-1.6.12.dist-info/METADATA
ppopt-1.6.12.dist-info/WHEEL
ppopt-1.6.12.dist-info/top_level.txt
ppopt-1.6.12.dist-info/RECORD
