Metadata-Version: 2.1
Name: ppopt
Version: 1.6.12
Summary: Extensible Multiparametric Solver in Python
Home-page: https://github.com/TAMUparametric/PPOPT
Author: Dustin R. Kenefake
Author-email: Dustin.Kenefake@tamu.edu
License: MIT
License-File: LICENSE
Requires-Dist: numpy
Requires-Dist: matplotlib
Requires-Dist: scipy
Requires-Dist: numba
Requires-Dist: gurobipy
Requires-Dist: pathos
Requires-Dist: plotly
Requires-Dist: daqp
Provides-Extra: optional
Requires-Dist: cvxopt ; extra == 'optional'
Requires-Dist: quadprog ; extra == 'optional'
Provides-Extra: test
Requires-Dist: pytest ; extra == 'test'
Requires-Dist: cvxopt ; extra == 'test'
Requires-Dist: quadprog ; extra == 'test'
